model_logger_dp-1.0.3.post2.dist-info/METADATA
model_logger_dp-1.0.3.post2.dist-info/WHEEL
model_logger_dp-1.0.3.post2.dist-info/entry_points.txt
model_logger_dp-1.0.3.post2.dist-info/licenses/LICENSE
model_logger_dp/__init__.py
model_logger_dp/constant.py
model_logger_dp/helper.py
model_logger_dp/logger.py
model_logger_dp/logger_decorator.py
model_logger_dp/version.py
model_logger_dp-1.0.3.post2.dist-info/RECORD
