Metadata-Version: 2.1
Name: model_logger_dp
Version: 1.0.3.post2
Summary: Model Logger for Pytorch
Keywords: python,logger,model
Author-Email: Ian Zhu <IanZhu@m.ldu.edu.cn>
License: MIT
Project-URL: homepage, https://github.com/10-4zz/model_logger_dp
Project-URL: repository, https://github.com/10-4zz/model_logger_dp
Requires-Python: >=3.8
